ete_ts/__init__.py
ete_ts/metrics.py
ete_ts-0.2.1.dist-info/licenses/LICENSE.md
ete_ts-0.2.1.dist-info/licenses/NOTICE.md
testing/__init__.py
testing/assertance_check.py
testing/features_correlation_rank.py
testing/test_complexity.py
testing/test_ete-ts.py
ete_ts-0.2.1.dist-info/METADATA
ete_ts-0.2.1.dist-info/WHEEL
ete_ts-0.2.1.dist-info/top_level.txt
ete_ts-0.2.1.dist-info/RECORD
