Metadata-Version: 2.4
Name: ete_ts
Version: 0.2.1
Summary: A package for analysing different caractheristics of time series data.
Home-page: https://github.com/franciscovmacieira/ete_ts.git
Author: Francisco Macieira
Classifier: Programming Language :: Python :: 3
Classifier: License :: OSI Approved :: GNU General Public License v3 (GPLv3)
Classifier: Operating System :: OS Independent
Requires-Python: >=3.9
License-File: LICENSE.md
License-File: NOTICE.md
Requires-Dist: numpy~=1.26.4
Requires-Dist: antropy~=0.1.9
Requires-Dist: pycatch22~=0.4.5
Requires-Dist: tsfel~=0.1.9
Requires-Dist: tsfeatures~=0.4.5
Requires-Dist: statsmodels~=0.14.4
Requires-Dist: ruptures~=1.1.9
Requires-Dist: scikit-learn~=1.6.1
Dynamic: author
Dynamic: classifier
Dynamic: description
Dynamic: description-content-type
Dynamic: home-page
Dynamic: license-file
Dynamic: requires-dist
Dynamic: requires-python
Dynamic: summary
